mpath/__init__.py
mpath/src/path.py
mpath-1.1.3.dist-info/LICENSE
mpath-1.1.3.dist-info/METADATA
mpath-1.1.3.dist-info/WHEEL
mpath-1.1.3.dist-info/top_level.txt
mpath-1.1.3.dist-info/RECORD
