Metadata-Version: 2.1
Name: mpath
Version: 1.1.3
Summary: give basic information about path
Author: Moses Dastmard
License-File: LICENSE
Requires-Dist: mclass
